L9110_I2C.py
mke_m17_micropython-0.1.4.dist-info/licenses/LICENSE
mke_m17_micropython-0.1.4.dist-info/METADATA
mke_m17_micropython-0.1.4.dist-info/WHEEL
mke_m17_micropython-0.1.4.dist-info/top_level.txt
mke_m17_micropython-0.1.4.dist-info/RECORD
