Metadata-Version: 2.4
Name: MKE-M17-MicroPython
Version: 0.1.4
Summary: A MicroPython driver for the L9110 motor controller over I2C
Author-email: Quy-An <quyan18b@gmail.com>
Project-URL: Homepage, https://github.com/Quy-An/MKE-M17-V2
Project-URL: Documentation, https://github.com/Quy-An/MKE-M17-V2/blob/main/README.md
Classifier: Programming Language :: Python :: Implementation :: MicroPython
Classifier: License :: OSI Approved :: MIT License
Classifier: Operating System :: OS Independent
Classifier: Topic :: Software Development :: Embedded Systems
License-File: LICENSE
Dynamic: license-file
